fastapi_advanced_rate_limiter/__init__.py
fastapi_advanced_rate_limiter/base.py
fastapi_advanced_rate_limiter/fix_sliding_window.py
fastapi_advanced_rate_limiter/fixed_window.py
fastapi_advanced_rate_limiter/leaky_bucket.py
fastapi_advanced_rate_limiter/queue_limiter.py
fastapi_advanced_rate_limiter/rate_limiter.py
fastapi_advanced_rate_limiter/sliding_window.py
fastapi_advanced_rate_limiter/sliding_window_log.py
fastapi_advanced_rate_limiter/token_bucket.py
fastapi_advanced_rate_limiter-2.1.0.dist-info/METADATA
fastapi_advanced_rate_limiter-2.1.0.dist-info/WHEEL
fastapi_advanced_rate_limiter-2.1.0.dist-info/top_level.txt
fastapi_advanced_rate_limiter-2.1.0.dist-info/RECORD
