Metadata-Version: 2.4
Name: fastapi-advanced-rate-limiter
Version: 2.1.0
Summary: High-performance, multi-algorithm rate limiting for FastAPI with Redis and in-memory backends
Home-page: https://github.com/awais7012/FastAPI-RateLimiter
Author: Ahmed Awais (Romeo)
Author-email: ahmadawaisgithub@gmail.com
Project-URL: Bug Tracker, https://github.com/awais7012/FastAPI-RateLimiter/issues
Project-URL: Documentation, https://github.com/awais7012/FastAPI-RateLimiter#readme
Project-URL: Source Code, https://github.com/awais7012/FastAPI-RateLimiter
Keywords: fastapi,rate-limiter,rate-limiting,throttling,api,redis,token-bucket,leaky-bucket,sliding-window
Classifier: Development Status :: 4 - Beta
Classifier: Intended Audience :: Developers
Classifier: License :: OSI Approved :: MIT License
Classifier: Programming Language :: Python :: 3
Classifier: Programming Language :: Python :: 3.8
Classifier: Programming Language :: Python :: 3.9
Classifier: Programming Language :: Python :: 3.10
Classifier: Programming Language :: Python :: 3.11
Classifier: Programming Language :: Python :: 3.12
Classifier: Framework :: FastAPI
Classifier: Topic :: Internet :: WWW/HTTP
Classifier: Topic :: Software Development :: Libraries :: Python Modules
Requires-Python: >=3.8
Requires-Dist: fastapi>=0.68.0
Provides-Extra: redis
Requires-Dist: redis>=4.0.0; extra == "redis"
Provides-Extra: dev
Requires-Dist: pytest>=7.0.0; extra == "dev"
Requires-Dist: pytest-asyncio>=0.18.0; extra == "dev"
Requires-Dist: black>=22.0.0; extra == "dev"
Requires-Dist: flake8>=4.0.0; extra == "dev"
Requires-Dist: mypy>=0.950; extra == "dev"
Provides-Extra: all
Requires-Dist: redis>=4.0.0; extra == "all"
Requires-Dist: pytest>=7.0.0; extra == "all"
Requires-Dist: pytest-asyncio>=0.18.0; extra == "all"
Dynamic: author
Dynamic: author-email
Dynamic: classifier
Dynamic: description
Dynamic: description-content-type
Dynamic: home-page
Dynamic: keywords
Dynamic: project-url
Dynamic: provides-extra
Dynamic: requires-dist
Dynamic: requires-python
Dynamic: summary
